flafl/__init__.py
flafl/bamboo.py
flafl/context.py
flafl/exceptions.py
flafl/helpers.py
flafl/jsonparser.py
flafl/strategies.py
flafl-0.0.6.dist-info/LICENSE
flafl-0.0.6.dist-info/METADATA
flafl-0.0.6.dist-info/WHEEL
flafl-0.0.6.dist-info/RECORD
