Metadata-Version: 2.1
Name: flafl
Version: 0.0.6
Summary: Flask application for listening to webhooks
Home-page: https://github.com/msleigh/flafl
License: Apache-2.0
Author: msleigh
Author-email: msleigh@noreply.users.github.com
Requires-Python: >=3.8,<4.0
Classifier: Development Status :: 1 - Planning
Classifier: License :: OSI Approved :: Apache Software License
Classifier: Natural Language :: English
Classifier: Operating System :: OS Independent
Classifier: Programming Language :: Python :: 3
Classifier: Programming Language :: Python :: 3.8
Classifier: Programming Language :: Python :: 3.9
Classifier: Programming Language :: Python :: 3.10
Classifier: Programming Language :: Python :: 3.11
Classifier: Programming Language :: Python :: 3
Requires-Dist: Flask (>=2.3.2,<3.0.0)
Requires-Dist: pyyaml (>=6.0,<7.0)
Requires-Dist: requests (>=2.30.0,<3.0.0)
Project-URL: Bug Tracker, https://github.com/msleigh/flafl/issues
Project-URL: CI, https://github.com/msleigh/flafl/actions
Project-URL: Changelog, https://github.com/msleigh/flafl/releases
